talos/__init__.py
talos/autom8/__init__.py
talos/autom8/automodel.py
talos/autom8/autoparams.py
talos/autom8/autopredict.py
talos/autom8/autoscan.py
talos/callbacks/__init__.py
talos/callbacks/experiment_log.py
talos/callbacks/power_draw.py
talos/commands/__init__.py
talos/commands/analyze.py
talos/commands/deploy.py
talos/commands/evaluate.py
talos/commands/predict.py
talos/commands/restore.py
talos/logging/__init__.py
talos/logging/logging_finish.py
talos/logging/logging_run.py
talos/logging/results.py
talos/metrics/__init__.py
talos/metrics/entropy.py
talos/metrics/keras_metrics.py
talos/model/__init__.py
talos/model/early_stopper.py
talos/model/hidden_layers.py
talos/model/ingest_model.py
talos/model/network_shape.py
talos/model/normalizers.py
talos/model/output_layer.py
talos/parameters/DistributeParamSpace.py
talos/parameters/ParamSpace.py
talos/parameters/__init__.py
talos/reducers/GamifyMap.py
talos/reducers/__init__.py
talos/reducers/correlation.py
talos/reducers/forrest.py
talos/reducers/gamify.py
talos/reducers/limit_by_metric.py
talos/reducers/local_strategy.py
talos/reducers/reduce_run.py
talos/reducers/reduce_utils.py
talos/reducers/sample_reducer.py
talos/reducers/trees.py
talos/scan/Scan.py
talos/scan/__init__.py
talos/scan/scan_addon.py
talos/scan/scan_finish.py
talos/scan/scan_prepare.py
talos/scan/scan_round.py
talos/scan/scan_run.py
talos/scan/scan_utils.py
talos/templates/__init__.py
talos/templates/datasets.py
talos/templates/models.py
talos/templates/params.py
talos/templates/pipelines.py
talos/utils/__init__.py
talos/utils/best_model.py
talos/utils/exceptions.py
talos/utils/generator.py
talos/utils/gpu_utils.py
talos/utils/load_model.py
talos/utils/power_draw_append.py
talos/utils/recover_best_model.py
talos/utils/rescale_meanzero.py
talos/utils/sequence_generator.py
talos/utils/test_utils.py
talos/utils/torch_history.py
talos/utils/validation_split.py
talos-1.4.dist-info/METADATA
talos-1.4.dist-info/WHEEL
talos-1.4.dist-info/licenses/LICENSE
talos-1.4.dist-info/RECORD
