Metadata-Version: 2.3
Name: talos
Version: 1.4
Summary: Talos Hyperparameter Tuning for Keras
Project-URL: Download, https://github.com/autonomio/talos/
Project-URL: Homepage, http://autonom.io
Author-email: Mikko Kotila <mailme@mikkokotila.com>
Maintainer-email: Mikko Kotila <mailme@mikkokotila.com>
License-Expression: MIT
License-File: LICENSE
Classifier: Intended Audience :: Science/Research
Classifier: License :: OSI Approved :: MIT License
Classifier: Operating System :: MacOS
Classifier: Operating System :: Microsoft :: Windows :: Windows 10
Classifier: Operating System :: POSIX
Classifier: Operating System :: Unix
Classifier: Programming Language :: Python :: 2.7
Classifier: Programming Language :: Python :: 3.5
Classifier: Programming Language :: Python :: 3.6
Classifier: Topic :: Scientific/Engineering :: Artificial Intelligence
Classifier: Topic :: Scientific/Engineering :: Human Machine Interfaces
Classifier: Topic :: Scientific/Engineering :: Mathematics
Requires-Dist: astetik
Requires-Dist: chances
Requires-Dist: kerasplotlib
Requires-Dist: numpy
Requires-Dist: pandas
Requires-Dist: requests
Requires-Dist: scikit-learn
Requires-Dist: statsmodels>=0.11.0
Requires-Dist: tensorflow==2.14.1
Requires-Dist: tqdm
Requires-Dist: wrangle
